ixnetwork/IxnConfigManagement.py
ixnetwork/IxnDynAttr.py
ixnetwork/IxnEmulationHost.py
ixnetwork/IxnEmulationHostManagement.py
ixnetwork/IxnEmulationHosts.py
ixnetwork/IxnFileManagement.py
ixnetwork/IxnHttp.py
ixnetwork/IxnMultivalue.py
ixnetwork/IxnObject.py
ixnetwork/IxnPortManagement.py
ixnetwork/IxnQuery.py
ixnetwork/IxnStatManagement.py
ixnetwork/__init__.py
ixnetwork/samples/Config.py
ixnetwork/samples/__init__.py
ixnetwork/samples/create/create_ipv4_topology.py
ixnetwork/samples/emulation_host/bgp-emulation-host-demo.ixncfg
ixnetwork/samples/emulation_host/bgp_emulation_host_demo.py
ixnetwork/samples/emulation_host/emulation-host-demo.ixncfg
ixnetwork/samples/emulation_host/emulation_host_demo.py
ixnetwork/samples/emulation_host/emulation_host_find.py
ixnetwork/samples/emulation_host/emulation_host_one_session.py
ixnetwork/samples/global/system_info.py
ixnetwork/samples/query/query.py
ixnetwork/samples/sessions/connect_gui.py
ixnetwork/samples/sessions/create_new_session.py
ixnetwork/samples/sessions/delete_sessions.py
ixnetwork/samples/sessions/reconnect_existing_session.py
ixnetwork_rest-0.55a50.dist-info/DESCRIPTION.rst
ixnetwork_rest-0.55a50.dist-info/METADATA
ixnetwork_rest-0.55a50.dist-info/RECORD
ixnetwork_rest-0.55a50.dist-info/WHEEL
ixnetwork_rest-0.55a50.dist-info/metadata.json
ixnetwork_rest-0.55a50.dist-info/top_level.txt
