Metadata-Version: 2.0
Name: ixnetwork-rest
Version: 0.55a50
Summary: IxNetwork REST API Client
Home-page: https://github.com/ajbalogh/ixnetwork_client_python
Author: andrey.balogh@gmail.com
Author-email: andrey.balogh@gmail.com
License: MIT
Keywords: ixnetwork rest automation development
Platform: UNKNOWN
Classifier: Development Status :: 3 - Alpha
Classifier: Intended Audience :: Developers
Classifier: Topic :: Software Development :: Build Tools
Classifier: License :: OSI Approved :: MIT License
Classifier: Programming Language :: Python :: 2.7
Classifier: Programming Language :: Python :: 3
Requires-Python: >=2.7, <4
